shadowlogger/__init__.py
shadowlogger/base_tracker.py
shadowlogger/intercept_handler.py
shadowlogger/shadowlogger.py
shadowlogger/shadowlogger_manager.py
shadowlogger/singleton.py
shadowlogger-0.1.1.dist-info/LICENSE
shadowlogger-0.1.1.dist-info/METADATA
shadowlogger-0.1.1.dist-info/WHEEL
shadowlogger-0.1.1.dist-info/top_level.txt
shadowlogger-0.1.1.dist-info/RECORD
