Metadata-Version: 2.1
Name: shadowlogger
Version: 0.1.1
Home-page: https://github.com/Capsize-Games/shadowlogger
Author: Capsize LLC
Author-email: contact@capsizegames.com
License: GPL-3.0
Requires-Python: >=3.10.0
License-File: LICENSE
